onboarding/__init__.py
onboarding/admin.py
onboarding/apps.py
onboarding/models.py
onboarding/tests.py
onboarding/views.py
onboarding/migrations/0001_initial.py
onboarding/migrations/__init__.py
django_models_pacakge_rinku_pace-1.1.0.dist-info/LICENSE
django_models_pacakge_rinku_pace-1.1.0.dist-info/METADATA
django_models_pacakge_rinku_pace-1.1.0.dist-info/WHEEL
django_models_pacakge_rinku_pace-1.1.0.dist-info/top_level.txt
django_models_pacakge_rinku_pace-1.1.0.dist-info/RECORD
